.DS_Store
gym_jiminy/rllib/__init__.py
gym_jiminy/rllib/curriculum.py
gym_jiminy/rllib/patches.py
gym_jiminy/rllib/ppo.py
gym_jiminy/rllib/py.typed
gym_jiminy/rllib/utilities.py
gym_jiminy_rllib-1.8.13.dist-info/METADATA
gym_jiminy_rllib-1.8.13.dist-info/WHEEL
gym_jiminy_rllib-1.8.13.dist-info/top_level.txt
gym_jiminy_rllib-1.8.13.dist-info/RECORD
