Metadata-Version: 2.2
Name: gym-jiminy-rllib
Version: 1.8.13
Summary: Specialized Reinforcement learning toolbox based on Ray RLlib for Gym Jiminy.
Author: Alexis Duburcq
Author-email: alexis.duburcq@gmail.com
Maintainer: Alexis Duburcq
License: MIT
Keywords: reinforcement-learning robotics gym jiminy
Classifier: Development Status :: 2 - Pre-Alpha
Classifier: Intended Audience :: Science/Research
Classifier: Topic :: Scientific/Engineering :: Artificial Intelligence
Classifier: Topic :: Software Development :: Libraries :: Python Modules
Classifier: License :: OSI Approved :: MIT License
Classifier: Programming Language :: Python :: 3.10
Classifier: Programming Language :: Python :: 3.11
Classifier: Programming Language :: Python :: 3.12
Classifier: Programming Language :: Python :: 3.13
Requires-Python: >=3.10,<3.14
Requires-Dist: gym-jiminy~=1.8.13
Requires-Dist: ray[rllib]<=2.40,>=2.38
Requires-Dist: tensorboardX
Requires-Dist: plotext>=5.0.0
Dynamic: author
Dynamic: author-email
Dynamic: classifier
Dynamic: keywords
Dynamic: license
Dynamic: maintainer
Dynamic: requires-dist
Dynamic: requires-python
Dynamic: summary
